spacetimelib/__init__.py
spacetimelib/basic_ops.py
spacetimelib/error_checking.py
spacetimelib/frame.py
spacetimelib/worldline.py
spacetimelib-0.0.2.dist-info/LICENSE
spacetimelib-0.0.2.dist-info/METADATA
spacetimelib-0.0.2.dist-info/WHEEL
spacetimelib-0.0.2.dist-info/top_level.txt
spacetimelib-0.0.2.dist-info/RECORD
