Metadata-Version: 2.1
Name: spacetimelib
Version: 0.0.2
Summary: Special relativity physics library for Python
Home-page: https://github.com/kurtamohler/spacetimelib
Author: Kurt Mohler
Author-email: Kurt Mohler <kurtamohler@gmail.com>
License: MIT License
Project-URL: Homepage, https://github.com/kurtamohler/spacetimelib
Project-URL: Bug Tracker, https://github.com/kurtamohler/spacetimelib/issues
Classifier: Programming Language :: Python :: 3
Classifier: License :: OSI Approved :: MIT License
Classifier: Operating System :: OS Independent
Requires-Python: >=3
License-File: LICENSE
Requires-Dist: numpy
